[
 {
  "align": "Left",
  "content": "<div style=\"text-align: left;\">\n<img src=\"/files/ERP  Team - Footer.png\" alt=\"MT-Letter Head\" width=\"598.0\" style=\"width: 598.0px;\">\n</div>",
  "disabled": 0,
  "docstatus": 0,
  "doctype": "Letter Head",
  "footer": null,
  "footer_align": "Left",
  "footer_image": null,
  "footer_image_height": 0.0,
  "footer_image_width": 0.0,
  "footer_script": null,
  "footer_source": "HTML",
  "header_script": null,
  "image": "/files/ERP  Team - Footer.png",
  "image_height": 83.055555556,
  "image_width": 598.0,
  "is_default": 1,
  "letter_head_name": "MT-Letter Head",
  "modified": "2024-01-15 11:25:44.636995",
  "name": "MT-Letter Head",
  "source": "Image"
 }
]